ListenerLibrary/__init__.py
ListenerLibrary/keywords.py
ListenerLibrary/version.py
robotframework_listenerlibrary-1.0.3.dist-info/METADATA
robotframework_listenerlibrary-1.0.3.dist-info/WHEEL
robotframework_listenerlibrary-1.0.3.dist-info/top_level.txt
robotframework_listenerlibrary-1.0.3.dist-info/RECORD
