Metadata-Version: 2.1
Name: robotframework-listenerlibrary
Version: 1.0.3
Summary: Robot Framework Listener Library
Home-page: https://github.com/sebastianciupinski/robotframework-listenerlibrary
Author: Sebastian Ciupinski
Author-email: sebastian.ciupinski+robotframework-listenerlibrary@gmail.com
License: UNKNOWN
Platform: UNKNOWN
Classifier: Programming Language :: Python
Classifier: License :: OSI Approved :: MIT License
Classifier: Operating System :: OS Independent
